<?xml version="1.0" encoding="UTF-8" standalone="no"?>
<theme>
<version><![CDATA[1.0.0]]></version>
<uiVersion>10</uiVersion>
<author><![CDATA[PedroZ]]></author>
<designer><![CDATA[PedroZ]]></designer>
<title><![CDATA[探·界&MIUI完美图标补全]]></title>
<description><![CDATA[探·界&MIUI 完美图标补全计划
基于探·界主题，补全/修复MIUI12默认主题中未适配以及适配不佳的图标。基于官方图标去除牛皮癣，制作成分层图标。
图标绘制：@潮留美海かり @PedroZ @Yife Playte @Eirperuier @Mastiff Li]]></description>
<authors>
<author locale="zh_CN"><![CDATA[PedroZ]]></author>
</authors>
<designers>
<designer locale="zh_CN"><![CDATA[PedroZ]]></designer>
</designers>
<titles>
<title locale="zh_CN"><![CDATA[探·界&MIUI完美图标补全]]></title>
</titles>
<descriptions>
<description locale="zh_CN"><![CDATA[探·界&MIUI 完美图标补全计划
基于探·界主题，补全/修复MIUI12默认主题中未适配以及适配不佳的图标。基于官方图标去除牛皮癣，制作成分层图标。
图标绘制：@潮留美海かり @PedroZ @Yife Playte @Eirperuier @Mastiff Li]]></description>
</descriptions>
</theme>
